{
  "cli": {
    "version": ">= 12.0.0"
  },
  "build": {
    "preview-student": {
      "distribution": "internal",
      "channel": "preview",
      "env": {
        "APP_VARIANT": "student"
      },
      "android": {
        "buildType": "apk"
      }
    },
    "production-student": {
      "distribution": "store",
      "channel": "production",
      "env": {
        "APP_VARIANT": "student"
      }
    }
  },
  "submit": {
    "production-student": {
      "ios": {
        "appleId": "",
        "ascAppId": "",
        "appleTeamId": ""
      }
    }
  }
}
